{
	"pages": [ //pages数组中第一项表示应用启动页，参考：https://uniapp.dcloud.io/collocation/pages
		{
			"path": "pages/index/index",
			"style": {
				"navigationBarTitleText": "首页"
			}
		},
		 {
			"path":"pages/search/search",
			 "style":{
				 "navigationBarTitleText":"发现"
			 }
		 },
		{
			"path": "pages/mine/mine",
			"style": {
				"navigationBarTitleText": "我的"
			}
		},
		{
			"path":"pages/register/entrance"
		},
		{
			"path":"pages/register/login"
		},
		{
			"path":"pages/register/regist"
		},
		{
			"path":"pages/register/forget"
		},
		{
			"path":"pages/index/intro"
		},
		{
			"path":"pages/detail/detail"
		},
		{
			"path":"pages/comment/comment"
		},
		{
			"path":"pages/mine/collect/collect",
			"style":{
				"navigationBarTitleText":"我的收藏"
			}
		},
		{
			"path":"pages/mine/message/message",
			"style":{
				"navigationBarBackgroundColor":"#FFFFFF",
				"navigationBarTitleText":"个人信息"
			}
		},
		{
			"path":"pages/mine/comment_history/comment_history",
			"style":{
				"navigationBarTitleText":"我的评论"
			}
		},
		{
			"path":"pages/mine/footprint/footprint",
			"style":{
				"navigationBarTitleText":"我的足迹"
			}
		}

	],
	"tabBar": {
		"color": "#7A7E83",
		"selectedColor": "#3cc51f",
		"borderStyle": "black",
		"backgroundColor": "#ffffff",
		"list": [{
			"pagePath": "pages/index/index",
			"text": "首页",
			"iconPath": "static/index/index.png",
			"selectedIconPath": "static/index/index-select.png"
		}, {
			"pagePath": "pages/search/search",
			"text": "发现",
			"iconPath": "static/find/find.png",
			"selectedIconPath": "static/find/find-select.png"
		}, {
			"pagePath": "pages/mine/mine",
			"text": "我的",
			"iconPath": "static/mine/mine.png",
			"selectedIconPath": "static/mine/mine-select.png"
		}]
	},
	"globalStyle": {
		"navigationBarTextStyle": "black",
		"navigationBarTitleText": "uni-app",
		"navigationBarBackgroundColor": "#F8F8F8",
		"backgroundColor": "#F8F8F8"
	}
}
